primeNumbersEIPCarvillac/__init__.py
primeNumbersEIPCarvillac-1.0.dist-info/LICENSE
primeNumbersEIPCarvillac-1.0.dist-info/METADATA
primeNumbersEIPCarvillac-1.0.dist-info/WHEEL
primeNumbersEIPCarvillac-1.0.dist-info/top_level.txt
primeNumbersEIPCarvillac-1.0.dist-info/RECORD
