Metadata-Version: 2.1
Name: primeNumbersEIPCarvillac
Version: 1.0
Summary: Returns all the primes numbers from 1 to N
Home-page: UNKNOWN
Author: Carlos Villacastín
Author-email: carlosvillacastinruiz@gmail.com
License: GNU GPLv3
Keywords: primenumbers prime eip
Platform: UNKNOWN
Classifier: Development Status :: 4 - Beta
Classifier: Intended Audience :: Developers
Classifier: Topic :: Utilities
Classifier: License :: OSI Approved :: GNU General Public License v3 (GPLv3)
Classifier: Programming Language :: Python :: 3
Classifier: Operating System :: OS Independent
